MANIFEST.in
setup.py
angel_fs/__init__.py
angel_fs/filesystem.py
angel_fs.egg-info/PKG-INFO
angel_fs.egg-info/SOURCES.txt
angel_fs.egg-info/dependency_links.txt
angel_fs.egg-info/entry_points.txt
angel_fs.egg-info/not-zip-safe
angel_fs.egg-info/requires.txt
angel_fs.egg-info/top_level.txt
angel_fs/utils/__init__.py
angel_fs/utils/config_util.py
etc/fs.conf
etc/logger.conf
examples/simple_start.py
scripts/fs_daemon