Metadata-Version: 1.1
Name: angel-fs
Version: 1.0.3
Summary: The filesystem of a distribute job scheduler named 'angel'
Home-page: https://pypi.python.org/pypi/angel_fs
Author: Lafite93
Author-email: 2273337844@qq.com
License: Apache
Keywords: angel filesystem
Platform: Linux
Platform: Unix
Classifier: Programming Language :: Python :: 3
Classifier: Programming Language :: Python :: 3.5
